just_config/__init__.py
just_config/configuration.py
just_config/version.py
just_config-24.1.dist-info/LICENSE
just_config-24.1.dist-info/METADATA
just_config-24.1.dist-info/WHEEL
just_config-24.1.dist-info/top_level.txt
just_config-24.1.dist-info/RECORD
