Metadata-Version: 2.1
Name: just-config
Version: 24.1
Summary: Minimalistic library to handle configuration for the application
Home-page: http://packages.python.org/just_config
Author: Alexander Pushkarev
Author-email: alexspush@gmail.com
License: MIT
License-File: LICENSE
